{"id":"hmsq2kbj4iv67nkjubl4ll1","title":"Q3. Have any of you certified multiple projects? (x3/x2)","desc":"","updated":1731180887759,"created":1727902286362,"custom":{},"fname":"1-audience-survey.q3","type":"note","vault":{"fsPath":"vault"},"contentHash":"f870240307c5d2a3b41990696a00c19c","links":[{"from":{"fname":"1-audience-survey","vaultName":"vault"},"type":"backlink","position":{"start":{"line":8,"column":1,"offset":67},"end":{"line":8,"column":25,"offset":91},"indent":[]},"value":"1-audience-survey.q3","alias":"1-audience-survey.q3"},{"from":{"fname":"1-audience-survey","vaultName":"vault"},"type":"backlink","position":{"start":{"line":20,"column":1,"offset":211},"end":{"line":20,"column":26,"offset":236},"indent":[]},"value":"1-audience-survey.q3"}],"anchors":{"notes":{"type":"header","text":"notes","value":"notes","line":8,"column":0,"depth":2}},"children":[],"parent":"py9pnyni5n8iwwbgqmfsad1","data":{}}
