{"id":"z3esa6d0s7y1ksnl2pr0uzv","title":"Automate Certification","desc":"","updated":1729024560656,"created":1729024369074,"custom":{},"fname":"3-user-stories.use-cases-list.automate-certification","type":"note","vault":{"fsPath":"vault"},"contentHash":"9653ad0beb99e56baf7290fe47368ebf","links":[{"from":{"fname":"3-user-stories.user-stories-list.developer-automate-certification","vaultName":"vault"},"type":"backlink","position":{"start":{"line":3,"column":11,"offset":72},"end":{"line":3,"column":67,"offset":128},"indent":[]},"value":"3-user-stories.use-cases-list.automate-certification","alias":"3-user-stories.use-cases-list.automate-certification"}],"anchors":{"notes":{"type":"header","text":"notes","value":"notes","line":8,"column":0,"depth":2}},"children":[],"parent":"0mp73mxrsqppact7oc0rluz","data":{}}
